mbddns/__init__.py
mbddns-0.1.2.dist-info/LICENSE
mbddns-0.1.2.dist-info/METADATA
mbddns-0.1.2.dist-info/WHEEL
mbddns-0.1.2.dist-info/top_level.txt
mbddns-0.1.2.dist-info/RECORD
