Metadata-Version: 1.0
Name: mbddns
Version: 0.1.2
Summary: Mythic Beasts Dynamic DNS updater
Home-page: https://github.com/thinkl33t/mb-ddns
Author: Bob Clough
Author-email: bob@clough.me
License: MIT
Platform: UNKNOWN
